oislutil/__init__.py
oislutil/slack.py
oislutil-0.0.1.dist-info/METADATA
oislutil-0.0.1.dist-info/WHEEL
oislutil-0.0.1.dist-info/top_level.txt
oislutil-0.0.1.dist-info/RECORD
