Metadata-Version: 2.1
Name: oislutil
Version: 0.0.1
Summary: Fun Utils for OISL
Home-page: https://github.com/SangsChicom/oisl-util
Author: TaeYoung.Kim
Author-email: falcon@yonsei.ac.kr
License: UNKNOWN
Keywords: oisl
Platform: UNKNOWN
Classifier: Programming Language :: Python :: 3
Classifier: Programming Language :: Python :: 3.2
Classifier: Programming Language :: Python :: 3.3
Classifier: Programming Language :: Python :: 3.4
Classifier: Programming Language :: Python :: 3.5
Classifier: Programming Language :: Python :: 3.6
Classifier: Programming Language :: Python :: 3.7
Requires-Python: >=3
Requires-Dist: requests
